mcp_server_zhxg_search/__init__.py
mcp_server_zhxg_search/__main__.py
mcp_server_zhxg_search/server.py
mcp_server_zhxg_search-0.1.1.dist-info/METADATA
mcp_server_zhxg_search-0.1.1.dist-info/WHEEL
mcp_server_zhxg_search-0.1.1.dist-info/entry_points.txt
mcp_server_zhxg_search-0.1.1.dist-info/top_level.txt
mcp_server_zhxg_search-0.1.1.dist-info/RECORD
