Metadata-Version: 2.4
Name: mcp-server-zhxg-search
Version: 0.1.1
Summary: 智慧星光互联网开源信息搜索工具
Requires-Python: >=3.12
Requires-Dist: aiohttp>=3.11.18
Requires-Dist: asyncio>=3.4.3
Requires-Dist: mcp>=1.9.0
Requires-Dist: openai>=1.79.0
Requires-Dist: openai-agents>=0.0.15
Requires-Dist: pydantic>=2.11.4
Requires-Dist: typing>=3.10.0.0
